README.rst
setup.cfg
setup.py
Flask_Neo4jDriver.egg-info/PKG-INFO
Flask_Neo4jDriver.egg-info/SOURCES.txt
Flask_Neo4jDriver.egg-info/dependency_links.txt
Flask_Neo4jDriver.egg-info/not-zip-safe
Flask_Neo4jDriver.egg-info/requires.txt
Flask_Neo4jDriver.egg-info/top_level.txt
flask_neo4j/__init__.py
flask_neo4j/driver.py
flask_neo4j/exceptions.py
flask_neo4j/model.py
flask_neo4j/validator.py