Metadata-Version: 1.2
Name: Flask-Neo4jDriver
Version: 0.2.0
Summary: Flask extension for official neo4j python driver.
Home-page: https://github.com/scbunn/flask-neo4jdriver
Author: Stephen Bunn
Author-email: scbunn@sbunn.org
License: GPLv3
Keywords: flask neo4j database graph
Platform: any
Classifier: Environment :: Web Environment
Classifier: Intended Audience :: Developers
Classifier: License :: OSI Approved :: GNU General Public License v3 (GPLv3)
Classifier: Operating System :: OS Independent
Classifier: Programming Language :: Python
Classifier: Topic :: Internet :: WWW/HTTP :: Dynamic Content
Classifier: Topic :: Software Development :: Libraries :: Python Modules
Classifier: Programming Language :: Python :: 3
Classifier: Programming Language :: Python :: 3.6
Requires-Python: >=3
